framedirect/__init__.py
framedirect-0.6.1.dist-info/licenses/LICENSE
framedirect-0.6.1.dist-info/METADATA
framedirect-0.6.1.dist-info/WHEEL
framedirect-0.6.1.dist-info/top_level.txt
framedirect-0.6.1.dist-info/RECORD
