Metadata-Version: 2.4
Name: framedirect
Version: 0.6.1
Summary: Una librería para dibujar píxeles usando el framebuffer de Linux en Python.
Home-page: https://github.com/gneval9/FrameDirect
Author: gneval9 Software
Author-email: gneval99@gmail.com
License: MIT
Classifier: Programming Language :: Python :: 3
Classifier: Programming Language :: Python :: 3.6
Classifier: Programming Language :: Python :: 3.10
Classifier: License :: OSI Approved :: MIT License
Classifier: Operating System :: POSIX :: Linux
Classifier: Topic :: Multimedia :: Graphics
Classifier: Intended Audience :: Developers
Requires-Python: >=3.6
License-File: LICENSE
Dynamic: author
Dynamic: author-email
Dynamic: classifier
Dynamic: description
Dynamic: description-content-type
Dynamic: home-page
Dynamic: license
Dynamic: license-file
Dynamic: requires-python
Dynamic: summary
